operation_log_service/__init__.py
operation_log_service/common_pb2.py
operation_log_service/common_pb2_grpc.py
operation_log_service/grpc_client.py
operation_log_service/model.py
operation_log_service/operationLogService_pb2.py
operation_log_service/operationLogService_pb2_grpc.py
operation_log_service/schema.py
longleding_operation_log_service_sdk-0.3.0.dist-info/LICENSE
longleding_operation_log_service_sdk-0.3.0.dist-info/METADATA
longleding_operation_log_service_sdk-0.3.0.dist-info/WHEEL
longleding_operation_log_service_sdk-0.3.0.dist-info/top_level.txt
longleding_operation_log_service_sdk-0.3.0.dist-info/RECORD
