Metadata-Version: 2.1
Name: longleding-operation-log-service-sdk
Version: 0.3.0
Summary: Longleding Operation Log Service SDK
Home-page: https://git.emhub.top/em/operation-log-service
Author: Shi Ran
Author-email: ran.shi@longleding.com
License: UNKNOWN
Platform: UNKNOWN
Classifier: Programming Language :: Python :: 3
Classifier: Topic :: System :: Logging
Requires-Python: >=3.6
Requires-Dist: attrs
Requires-Dist: grpcio
Requires-Dist: marshmallow
